multistamper/__init__.py
multistamper/stamp_cli.py
multistamper/core/__init__.py
multistamper/core/apiclient.py
multistamper/core/datasource.py
multistamper/core/pipeline.py
multistamper-0.1.1.dist-info/METADATA
multistamper-0.1.1.dist-info/WHEEL
multistamper-0.1.1.dist-info/entry_points.txt
multistamper-0.1.1.dist-info/top_level.txt
multistamper-0.1.1.dist-info/RECORD
