Metadata-Version: 2.4
Name: multistamper
Version: 0.1.1
Summary: Multistamper CLI tool to multiple stamp files using vBase API
Requires-Python: >=3.8
Requires-Dist: python-dotenv
Requires-Dist: requests
